fias/__init__.py
fias/admin.py
fias/base.py
fias/base_models.py
fias/compat.py
fias/config.py
fias/exceptions.py
fias/forms.py
fias/publish_tools.py
fias/routers.py
fias/urls.py
fias/version.py
fias/views.py
fias/weights.py
fias/fields/__init__.py
fias/fields/address.py
fias/fields/uuid.py
fias/importer/__init__.py
fias/importer/client.py
fias/importer/commands.py
fias/importer/filters.py
fias/importer/indexes.py
fias/importer/loader.py
fias/importer/log.py
fias/importer/parsers.py
fias/importer/signals.py
fias/importer/timer.py
fias/importer/version.py
fias/importer/source/__init__.py
fias/importer/source/archive.py
fias/importer/source/directory.py
fias/importer/source/tablelist.py
fias/importer/source/wrapper.py
fias/importer/table/__init__.py
fias/importer/table/dbf.py
fias/importer/table/table.py
fias/importer/table/xml.py
fias/locale/ru/LC_MESSAGES/django.mo
fias/management/__init__.py
fias/management/commands/__init__.py
fias/management/commands/fias.py
fias/management/commands/fias_check_models.py
fias/management/commands/fias_duplicates.py
fias/management/commands/fias_generate_base_models.py
fias/management/commands/fias_suggest.py
fias/management/commands/fias_update_schema.py
fias/management/commands/fiasinfo.py
fias/management/utils/__init__.py
fias/management/utils/weights.py
fias/migrations/0001_initial.py
fias/migrations/__init__.py
fias/models/__init__.py
fias/models/address.py
fias/models/addrobj.py
fias/models/house.py
fias/models/landmark.py
fias/models/normdoc.py
fias/models/room.py
fias/models/socrbase.py
fias/models/sphinx.py
fias/models/status.py
fias/models/stead.py
fias/models/version.py
fias/suggest/__init__.py
fias/suggest/backends/__init__.py
fias/suggest/backends/noop/__init__.py
fias/suggest/backends/noop/backend.py
fias/suggest/backends/noop/urls.py
fias/suggest/backends/noop/views.py
fias/suggest/backends/noop/management/__init__.py
fias/suggest/backends/noop/management/command.py
fias/suggest/backends/sphinx/__init__.py
m3_django_fias-2.0.1.dist-info/LICENSE
m3_django_fias-2.0.1.dist-info/METADATA
m3_django_fias-2.0.1.dist-info/WHEEL
m3_django_fias-2.0.1.dist-info/top_level.txt
m3_django_fias-2.0.1.dist-info/RECORD
