Metadata-Version: 2.1
Name: m3-django-fias
Version: 2.0.1
Summary: FIAS Django integration for m3
Home-page: UNKNOWN
Author: BARS Group
Author-email: bars@bars.group
License: MIT license
Platform: UNKNOWN
Classifier: Development Status :: 4 - Beta
Classifier: Intended Audience :: Developers
Classifier: Intended Audience :: Science/Research
Classifier: License :: OSI Approved :: MIT License
Classifier: Natural Language :: Russian
Classifier: Programming Language :: Python
Classifier: Programming Language :: Python :: 2
Classifier: Programming Language :: Python :: 2.7
Classifier: Programming Language :: Python :: 3
Classifier: Programming Language :: Python :: 3.4
Classifier: Programming Language :: Python :: 3.5
Classifier: Topic :: Software Development :: Libraries :: Python Modules
Requires-Dist: django (==1.9.13)
Requires-Dist: django-select2 (==5.11.1)
Requires-Dist: django-appconf (==1.0.2)
Requires-Dist: rarfile (==3.1)
Requires-Dist: six
Requires-Dist: lxml
Requires-Dist: unrar
Requires-Dist: zeep (>=0.17.0)
Requires-Dist: dbfread (>=2.0.0)
Requires-Dist: progress (<1.5)
Requires-Dist: requests
Requires-Dist: twine (==1.15.0)
Requires-Dist: GitPython (==2.1.15)
Provides-Extra: mysql
Requires-Dist: mysqlclient (!=1.3.8) ; extra == 'mysql'
